Metadata-Version: 2.1
Name: terminalplay
Version: 1.0.26
Summary: Play videos on your terminal; Works on windows as well as linux;The video played will also have color and sound :)
Home-page: https://github.com/merwin-asm/Terminal_Play
Author: Merwin JD
Author-email: merwin@fbi.ac
License: MIT
Project-URL: Bug Tracker, https://github.com/merwin-asm/Terminal_Play/issues
Keywords: terminalplay,play videos,terminal
Platform: windows
Platform: linux
Classifier: Development Status :: 1 - Planning
Classifier: Intended Audience :: Developers
Classifier: Programming Language :: Python :: 3
Classifier: Operating System :: Unix
Classifier: Operating System :: MacOS :: MacOS X
Classifier: Operating System :: Microsoft :: Windows
License-File: LICENSE
